Workbook

Sheet Painel
B2: PAINEL DE CUSTOS DA CASA
B3: Este painel é um resumo de conferência. A análise completa fica no site.
B5: Competência (AAAA-MM): | C5: 2026-01 | D5: ← altere aqui
B7: Total de Entradas | C7: =SUMIFS(Lancamentos!$L:$L,Lancamentos!$C:$C,$C$5,Lancamentos!$D:$D,"Entrada") -> 7500
B8: Total de Saídas | C8: =SUMIFS(Lancamentos!$L:$L,Lancamentos!$C:$C,$C$5,Lancamentos!$D:$D,"Saída") -> 3480.45
B9: Saldo do Mês | C9: =C7-C8 -> 4019.55
B10: Gasto no crédito | C10: =SUMIFS(Lancamentos!$L:$L,Lancamentos!$C:$C,$C$5,Lancamentos!$H:$H,"Crédito") -> 1280.45
B11: Ainda a pagar | C11: =SUMIFS(Lancamentos!$L:$L,Lancamentos!$C:$C,$C$5,Lancamentos!$D:$D,"Saída",Lancamentos!$M:$M,"Não") -> 1280.45
B13: GASTOS POR CATEGORIA | H13: EVOLUÇÃO DO ANO
B14: Categoria | C14: Gasto | D14: % | E14: Orçamento | F14: Diferença | H14: Competência | I14: Entradas | J14: Saídas | K14: Saldo | L14: Acumulado
B15: Aluguel/Condomínio | C15: =SUMIFS(Lancamentos!$L:$L,Lancamentos!$C:$C,$C$5,Lancamentos!$F:$F,$B15) -> 2200 | D15: =IF($C$8=0,0,C15/$C$8) -> 0.63210217 | E15: =IFERROR(INDEX(Orcamento!$B:$B,MATCH($B15,Orcamento!$A:$A,0)),0) -> 0 | F15: =IF(E15=0,"",E15-C15) | H15: 2026-01 | I15: =SUMIFS(Lancamentos!$L:$L,Lancamentos!$C:$C,$H15,Lancamentos!$D:$D,"Entrada") -> 7500 | J15: =SUMIFS(Lancamentos!$L:$L,Lancamentos!$C:$C,$H15,Lancamentos!$D:$D,"Saída") -> 3480.45 | K15: =I15-J15 -> 4019.55 | L15: =SUM($K$15:K15) -> 4019.55
B16: Contas da casa (luz/água/gás) | C16: =SUMIFS(Lancamentos!$L:$L,Lancamentos!$C:$C,$C$5,Lancamentos!$F:$F,$B16) -> 0 | D16: =IF($C$8=0,0,C16/$C$8) -> 0 | E16: =IFERROR(INDEX(Orcamento!$B:$B,MATCH($B16,Orcamento!$A:$A,0)),0) -> 0 | F16: =IF(E16=0,"",E16-C16) | H16: 2026-02 | I16: =SUMIFS(Lancamentos!$L:$L,Lancamentos!$C:$C,$H16,Lancamentos!$D:$D,"Entrada") -> 0 | J16: =SUMIFS(Lancamentos!$L:$L,Lancamentos!$C:$C,$H16,Lancamentos!$D:$D,"Saída") -> 420 | K16: =I16-J16 -> -420 | L16: =SUM($K$15:K16) -> 3599.55
B17: Internet/Telefone | C17: =SUMIFS(Lancamentos!$L:$L,Lancamentos!$C:$C,$C$5,Lancamentos!$F:$F,$B17) -> 0 | D17: =IF($C$8=0,0,C17/$C$8) -> 0 | E17: =IFERROR(INDEX(Orcamento!$B:$B,MATCH($B17,Orcamento!$A:$A,0)),0) -> 0 | F17: =IF(E17=0,"",E17-C17) | H17: 2026-03 | I17: =SUMIFS(Lancamentos!$L:$L,Lancamentos!$C:$C,$H17,Lancamentos!$D:$D,"Entrada") -> 0 | J17: =SUMIFS(Lancamentos!$L:$L,Lancamentos!$C:$C,$H17,Lancamentos!$D:$D,"Saída") -> 0 | K17: =I17-J17 -> 0 | L17: =SUM($K$15:K17) -> 3599.55
B18: Manutenção/Móveis | C18: =SUMIFS(Lancamentos!$L:$L,Lancamentos!$C:$C,$C$5,Lancamentos!$F:$F,$B18) -> 420 | D18: =IF($C$8=0,0,C18/$C$8) -> 0.12067405 | E18: =IFERROR(INDEX(Orcamento!$B:$B,MATCH($B18,Orcamento!$A:$A,0)),0) -> 0 | F18: =IF(E18=0,"",E18-C18) | H18: 2026-04 | I18: =SUMIFS(Lancamentos!$L:$L,Lancamentos!$C:$C,$H18,Lancamentos!$D:$D,"Entrada") -> 0 | J18: =SUMIFS(Lancamentos!$L:$L,Lancamentos!$C:$C,$H18,Lancamentos!$D:$D,"Saída") -> 0 | K18: =I18-J18 -> 0 | L18: =SUM($K$15:K18) -> 3599.55
B19: Mercado | C19: =SUMIFS(Lancamentos!$L:$L,Lancamentos!$C:$C,$C$5,Lancamentos!$F:$F,$B19) -> 860.45 | D19: =IF($C$8=0,0,C19/$C$8) -> 0.24722378 | E19: =IFERROR(INDEX(Orcamento!$B:$B,MATCH($B19,Orcamento!$A:$A,0)),0) -> 0 | F19: =IF(E19=0,"",E19-C19) | H19: 2026-05 | I19: =SUMIFS(Lancamentos!$L:$L,Lancamentos!$C:$C,$H19,Lancamentos!$D:$D,"Entrada") -> 0 | J19: =SUMIFS(Lancamentos!$L:$L,Lancamentos!$C:$C,$H19,Lancamentos!$D:$D,"Saída") -> 0 | K19: =I19-J19 -> 0 | L19: =SUM($K$15:K19) -> 3599.55
B20: Restaurantes/Delivery | C20: =SUMIFS(Lancamentos!$L:$L,Lancamentos!$C:$C,$C$5,Lancamentos!$F:$F,$B20) -> 0 | D20: =IF($C$8=0,0,C20/$C$8) -> 0 | E20: =IFERROR(INDEX(Orcamento!$B:$B,MATCH($B20,Orcamento!$A:$A,0)),0) -> 0 | F20: =IF(E20=0,"",E20-C20) | H20: 2026-06 | I20: =SUMIFS(Lancamentos!$L:$L,Lancamentos!$C:$C,$H20,Lancamentos!$D:$D,"Entrada") -> 0 | J20: =SUMIFS(Lancamentos!$L:$L,Lancamentos!$C:$C,$H20,Lancamentos!$D:$D,"Saída") -> 0 | K20: =I20-J20 -> 0 | L20: =SUM($K$15:K20) -> 3599.55
B21: Combustível | C21: =SUMIFS(Lancamentos!$L:$L,Lancamentos!$C:$C,$C$5,Lancamentos!$F:$F,$B21) -> 0 | D21: =IF($C$8=0,0,C21/$C$8) -> 0 | E21: =IFERROR(INDEX(Orcamento!$B:$B,MATCH($B21,Orcamento!$A:$A,0)),0) -> 0 | F21: =IF(E21=0,"",E21-C21) | H21: 2026-07 | I21: =SUMIFS(Lancamentos!$L:$L,Lancamentos!$C:$C,$H21,Lancamentos!$D:$D,"Entrada") -> 0 | J21: =SUMIFS(Lancamentos!$L:$L,Lancamentos!$C:$C,$H21,Lancamentos!$D:$D,"Saída") -> 0 | K21: =I21-J21 -> 0 | L21: =SUM($K$15:K21) -> 3599.55
B22: Transporte/App | C22: =SUMIFS(Lancamentos!$L:$L,Lancamentos!$C:$C,$C$5,Lancamentos!$F:$F,$B22) -> 0 | D22: =IF($C$8=0,0,C22/$C$8) -> 0 | E22: =IFERROR(INDEX(Orcamento!$B:$B,MATCH($B22,Orcamento!$A:$A,0)),0) -> 0 | F22: =IF(E22=0,"",E22-C22) | H22: 2026-08 | I22: =SUMIFS(Lancamentos!$L:$L,Lancamentos!$C:$C,$H22,Lancamentos!$D:$D,"Entrada") -> 0 | J22: =SUMIFS(Lancamentos!$L:$L,Lancamentos!$C:$C,$H22,Lancamentos!$D:$D,"Saída") -> 0 | K22: =I22-J22 -> 0 | L22: =SUM($K$15:K22) -> 3599.55
B23: Veículo (seguro/IPVA/manutenção) | C23: =SUMIFS(Lancamentos!$L:$L,Lancamentos!$C:$C,$C$5,Lancamentos!$F:$F,$B23) -> 0 | D23: =IF($C$8=0,0,C23/$C$8) -> 0 | E23: =IFERROR(INDEX(Orcamento!$B:$B,MATCH($B23,Orcamento!$A:$A,0)),0) -> 0 | F23: =IF(E23=0,"",E23-C23) | H23: 2026-09 | I23: =SUMIFS(Lancamentos!$L:$L,Lancamentos!$C:$C,$H23,Lancamentos!$D:$D,"Entrada") -> 0 | J23: =SUMIFS(Lancamentos!$L:$L,Lancamentos!$C:$C,$H23,Lancamentos!$D:$D,"Saída") -> 0 | K23: =I23-J23 -> 0 | L23: =SUM($K$15:K23) -> 3599.55
B24: Plano de Saúde | C24: =SUMIFS(Lancamentos!$L:$L,Lancamentos!$C:$C,$C$5,Lancamentos!$F:$F,$B24) -> 0 | D24: =IF($C$8=0,0,C24/$C$8) -> 0 | E24: =IFERROR(INDEX(Orcamento!$B:$B,MATCH($B24,Orcamento!$A:$A,0)),0) -> 0 | F24: =IF(E24=0,"",E24-C24) | H24: 2026-10 | I24: =SUMIFS(Lancamentos!$L:$L,Lancamentos!$C:$C,$H24,Lancamentos!$D:$D,"Entrada") -> 0 | J24: =SUMIFS(Lancamentos!$L:$L,Lancamentos!$C:$C,$H24,Lancamentos!$D:$D,"Saída") -> 0 | K24: =I24-J24 -> 0 | L24: =SUM($K$15:K24) -> 3599.55
B25: Saúde/Farmácia | C25: =SUMIFS(Lancamentos!$L:$L,Lancamentos!$C:$C,$C$5,Lancamentos!$F:$F,$B25) -> 0 | D25: =IF($C$8=0,0,C25/$C$8) -> 0 | E25: =IFERROR(INDEX(Orcamento!$B:$B,MATCH($B25,Orcamento!$A:$A,0)),0) -> 0 | F25: =IF(E25=0,"",E25-C25) | H25: 2026-11 | I25: =SUMIFS(Lancamentos!$L:$L,Lancamentos!$C:$C,$H25,Lancamentos!$D:$D,"Entrada") -> 0 | J25: =SUMIFS(Lancamentos!$L:$L,Lancamentos!$C:$C,$H25,Lancamentos!$D:$D,"Saída") -> 0 | K25: =I25-J25 -> 0 | L25: =SUM($K$15:K25) -> 3599.55
B26: Educação | C26: =SUMIFS(Lancamentos!$L:$L,Lancamentos!$C:$C,$C$5,Lancamentos!$F:$F,$B26) -> 0 | D26: =IF($C$8=0,0,C26/$C$8) -> 0 | E26: =IFERROR(INDEX(Orcamento!$B:$B,MATCH($B26,Orcamento!$A:$A,0)),0) -> 0 | F26: =IF(E26=0,"",E26-C26) | H26: 2026-12 | I26: =SUMIFS(Lancamentos!$L:$L,Lancamentos!$C:$C,$H26,Lancamentos!$D:$D,"Entrada") -> 0 | J26: =SUMIFS(Lancamentos!$L:$L,Lancamentos!$C:$C,$H26,Lancamentos!$D:$D,"Saída") -> 0 | K26: =I26-J26 -> 0 | L26: =SUM($K$15:K26) -> 3599.55
B27: Assinaturas/Streaming | C27: =SUMIFS(Lancamentos!$L:$L,Lancamentos!$C:$C,$C$5,Lancamentos!$F:$F,$B27) -> 0 | D27: =IF($C$8=0,0,C27/$C$8) -> 0 | E27: =IFERROR(INDEX(Orcamento!$B:$B,MATCH($B27,Orcamento!$A:$A,0)),0) -> 0 | F27: =IF(E27=0,"",E27-C27) | H27: TOTAL | I27: =SUM(I15:I26) -> 7500 | J27: =SUM(J15:J26) -> 3900.45 | K27: =I27-J27 -> 3599.55 | L27: =L26 -> 3599.55
B28: Lazer | C28: =SUMIFS(Lancamentos!$L:$L,Lancamentos!$C:$C,$C$5,Lancamentos!$F:$F,$B28) -> 0 | D28: =IF($C$8=0,0,C28/$C$8) -> 0 | E28: =IFERROR(INDEX(Orcamento!$B:$B,MATCH($B28,Orcamento!$A:$A,0)),0) -> 0 | F28: =IF(E28=0,"",E28-C28)
B29: Vestuário | C29: =SUMIFS(Lancamentos!$L:$L,Lancamentos!$C:$C,$C$5,Lancamentos!$F:$F,$B29) -> 0 | D29: =IF($C$8=0,0,C29/$C$8) -> 0 | E29: =IFERROR(INDEX(Orcamento!$B:$B,MATCH($B29,Orcamento!$A:$A,0)),0) -> 0 | F29: =IF(E29=0,"",E29-C29)
B30: Viagem | C30: =SUMIFS(Lancamentos!$L:$L,Lancamentos!$C:$C,$C$5,Lancamentos!$F:$F,$B30) -> 0 | D30: =IF($C$8=0,0,C30/$C$8) -> 0 | E30: =IFERROR(INDEX(Orcamento!$B:$B,MATCH($B30,Orcamento!$A:$A,0)),0) -> 0 | F30: =IF(E30=0,"",E30-C30) | H30: Amarelo = célula que você edita. O resto é fórmula, não digite por cima.
B31: Pets | C31: =SUMIFS(Lancamentos!$L:$L,Lancamentos!$C:$C,$C$5,Lancamentos!$F:$F,$B31) -> 0 | D31: =IF($C$8=0,0,C31/$C$8) -> 0 | E31: =IFERROR(INDEX(Orcamento!$B:$B,MATCH($B31,Orcamento!$A:$A,0)),0) -> 0 | F31: =IF(E31=0,"",E31-C31)
B32: Presentes/Doações | C32: =SUMIFS(Lancamentos!$L:$L,Lancamentos!$C:$C,$C$5,Lancamentos!$F:$F,$B32) -> 0 | D32: =IF($C$8=0,0,C32/$C$8) -> 0 | E32: =IFERROR(INDEX(Orcamento!$B:$B,MATCH($B32,Orcamento!$A:$A,0)),0) -> 0 | F32: =IF(E32=0,"",E32-C32)
B33: Impostos/Taxas | C33: =SUMIFS(Lancamentos!$L:$L,Lancamentos!$C:$C,$C$5,Lancamentos!$F:$F,$B33) -> 0 | D33: =IF($C$8=0,0,C33/$C$8) -> 0 | E33: =IFERROR(INDEX(Orcamento!$B:$B,MATCH($B33,Orcamento!$A:$A,0)),0) -> 0 | F33: =IF(E33=0,"",E33-C33)
B34: Empréstimo/Financiamento | C34: =SUMIFS(Lancamentos!$L:$L,Lancamentos!$C:$C,$C$5,Lancamentos!$F:$F,$B34) -> 0 | D34: =IF($C$8=0,0,C34/$C$8) -> 0 | E34: =IFERROR(INDEX(Orcamento!$B:$B,MATCH($B34,Orcamento!$A:$A,0)),0) -> 0 | F34: =IF(E34=0,"",E34-C34)
B35: Investimento/Reserva | C35: =SUMIFS(Lancamentos!$L:$L,Lancamentos!$C:$C,$C$5,Lancamentos!$F:$F,$B35) -> 0 | D35: =IF($C$8=0,0,C35/$C$8) -> 0 | E35: =IFERROR(INDEX(Orcamento!$B:$B,MATCH($B35,Orcamento!$A:$A,0)),0) -> 0 | F35: =IF(E35=0,"",E35-C35)
B36: Tarifas bancárias | C36: =SUMIFS(Lancamentos!$L:$L,Lancamentos!$C:$C,$C$5,Lancamentos!$F:$F,$B36) -> 0 | D36: =IF($C$8=0,0,C36/$C$8) -> 0 | E36: =IFERROR(INDEX(Orcamento!$B:$B,MATCH($B36,Orcamento!$A:$A,0)),0) -> 0 | F36: =IF(E36=0,"",E36-C36)
B37: Outros | C37: =SUMIFS(Lancamentos!$L:$L,Lancamentos!$C:$C,$C$5,Lancamentos!$F:$F,$B37) -> 0 | D37: =IF($C$8=0,0,C37/$C$8) -> 0 | E37: =IFERROR(INDEX(Orcamento!$B:$B,MATCH($B37,Orcamento!$A:$A,0)),0) -> 0 | F37: =IF(E37=0,"",E37-C37)
B38: TOTAL | C38: =SUM(C15:C37) -> 3480.45 | D38: =IF($C$8=0,0,C38/$C$8) -> 1 | E38: =SUM(E15:E37) -> 0 | F38: =E38-C38 -> -3480.45

Sheet Lancamentos
A1: id | B1: data | C1: competencia | D1: tipo | E1: descricao | F1: categoria | G1: grupo | H1: forma_pagamento | I1: cartao | J1: parcela | K1: parcelas_total | L1: valor | M1: pago | N1: obs
A2: EXEMPLO-1 | B2: 2026-01-05 | C2: 2026-01 | D2: Entrada | E2: Salário Ricardo | F2: Salário | G2: Receita | H2: Pix | J2: 1 | K2: 1 | L2: 7500 | M2: Sim | N2: apague esta linha
A3: EXEMPLO-2 | B3: 2026-01-07 | C3: 2026-01 | D3: Saída | E3: Aluguel janeiro | F3: Aluguel/Condomínio | G3: Moradia | H3: Boleto | J3: 1 | K3: 1 | L3: 2200 | M3: Sim | N3: apague esta linha
A4: EXEMPLO-3 | B4: 2026-01-12 | C4: 2026-01 | D4: Saída | E4: Compra mensal Assaí | F4: Mercado | G4: Alimentação | H4: Crédito | I4: NU RICARDO | J4: 1 | K4: 1 | L4: 860.45 | M4: Não | N4: apague esta linha
A5: EXEMPLO-4 | B5: 2026-01-20 | C5: 2026-01 | D5: Saída | E5: Geladeira 1/10 | F5: Manutenção/Móveis | G5: Moradia | H5: Crédito | I5: VISA RICARDO | J5: 1 | K5: 10 | L5: 420 | M5: Não | N5: parcela 1 de 10
A6: EXEMPLO-5 | B6: 2026-01-20 | C6: 2026-02 | D6: Saída | E6: Geladeira 2/10 | F6: Manutenção/Móveis | G6: Moradia | H6: Crédito | I6: VISA RICARDO | J6: 2 | K6: 10 | L6: 420 | M6: Não | N6: cai em fevereiro

Sheet Categorias
A1: categoria | B1: grupo | C1: tipo | D1: essencial
A2: Aluguel/Condomínio | B2: Moradia | C2: Saída | D2: Sim
A3: Contas da casa (luz/água/gás) | B3: Moradia | C3: Saída | D3: Sim
A4: Internet/Telefone | B4: Moradia | C4: Saída | D4: Sim
A5: Manutenção/Móveis | B5: Moradia | C5: Saída | D5: Não
A6: Mercado | B6: Alimentação | C6: Saída | D6: Sim
A7: Restaurantes/Delivery | B7: Alimentação | C7: Saída | D7: Não
A8: Combustível | B8: Transporte | C8: Saída | D8: Sim
A9: Transporte/App | B9: Transporte | C9: Saída | D9: Não
A10: Veículo (seguro/IPVA/manutenção) | B10: Transporte | C10: Saída | D10: Sim
A11: Plano de Saúde | B11: Saúde | C11: Saída | D11: Sim
A12: Saúde/Farmácia | B12: Saúde | C12: Saída | D12: Sim
... A28: Rendimentos/Investimentos | B28: Receita | C28: Entrada | D28: -

Sheet Cartoes
A1: cartao | B1: titular | C1: dia_fechamento | D1: dia_vencimento | E1: limite
A2: NU RICARDO | B2: Ricardo | C2: 3 | D2: 10 | E2: 0
A3: VISA RICARDO | B3: Ricardo | C3: 8 | D3: 12 | E3: 0
A4: NU HELENA | B4: Helena | C4: 20 | D4: 24 | E4: 0

Sheet Orcamento
A1: categoria | B1: limite_mensal
A2: Aluguel/Condomínio | B2: 0
A3: Contas da casa (luz/água/gás) | B3: 0
A4: Internet/Telefone | B4: 0
A5: Manutenção/Móveis | B5: 0
A6: Mercado | B6: 0
A7: Restaurantes/Delivery | B7: 0
A8: Combustível | B8: 0
A9: Transporte/App | B9: 0
A10: Veículo (seguro/IPVA/manutenção) | B10: 0
A11: Plano de Saúde | B11: 0
A12: Saúde/Farmácia | B12: 0
A13: Educação | B13: 0
... A24: Outros | B24: 0
A26: Preencha só as categorias que você quer limitar. Deixe 0 para ignorar.

Sheet Leia-me
B2: COMO ESTA PLANILHA FUNCIONA
B4: A regra de ouro: TODO lançamento — entrada, saída, dinheiro, débito ou cartão — vai numa
B5: única aba: Lancamentos. Não existe mais uma aba por mês nem uma aba por cartão.
B7: AS COLUNAS
B8: id — código único da linha. O site preenche sozinho. Se digitar na mão, use qualquer texto único.
B9: data — quando o gasto aconteceu (AAAA-MM-DD).
B10: competencia — em que mês esse valor pesa no bolso (AAAA-MM). É por AQUI que tudo é somado.
B11: Numa compra parcelada, cada parcela vira uma linha, com a mesma data e competências diferentes.
B12: tipo — Entrada ou Saída.
B13: descricao — texto livre.
B14: categoria — escolha da lista (aba Categorias). Uma lista só, valendo para tudo.
B15: grupo — preenchido pelo site a partir da categoria. Serve para agrupar no painel.
... B33: Ajuste os cartões e os dias de fechamento na aba Cartoes.
